les_louisdelatech/__init__.py
les_louisdelatech/bot.py
les_louisdelatech/main.py
les_louisdelatech/extensions/cats.py
les_louisdelatech/extensions/config.py
les_louisdelatech/extensions/hello_asso.py
les_louisdelatech/extensions/management.py
les_louisdelatech/extensions/otp.py
les_louisdelatech/extensions/task.py
les_louisdelatech/extensions/user.py
les_louisdelatech/models/__init__.py
les_louisdelatech/models/otp.py
les_louisdelatech/templates/discord/base.j2
les_louisdelatech/templates/discord/ca.j2
les_louisdelatech/templates/discord/logistique.j2
les_louisdelatech/templates/discord/marketing.j2
les_louisdelatech/templates/discord/reset_password.j2
les_louisdelatech/templates/discord/scene.j2
les_louisdelatech/templates/discord/technique.j2
les_louisdelatech/templates/discord/tournoi.j2
les_louisdelatech/templates/google/gmail_signature.j2
les_louisdelatech/utils/LouisDeLaTechError.py
les_louisdelatech/utils/User.py
les_louisdelatech/utils/discord.py
les_louisdelatech/utils/gsuite.py
les_louisdelatech/utils/hello_asso.py
les_louisdelatech/utils/password.py
les_louisdelatech-0.5.3.dist-info/METADATA
les_louisdelatech-0.5.3.dist-info/WHEEL
les_louisdelatech-0.5.3.dist-info/licenses/LICENSE
les_louisdelatech-0.5.3.dist-info/licenses/LICENSE.fr
les_louisdelatech-0.5.3.dist-info/RECORD
