Metadata-Version: 2.4
Name: les-louisdelatech
Version: 0.5.3
Summary: LouisDeLaTech is a discord bot manager for Lyon e-Sport
Project-URL: Homepage, https://github.com/lyon-esport/LouisDeLaTech
Project-URL: Repository, https://github.com/lyon-esport/LouisDeLaTech
Project-URL: Issues, https://github.com/lyon-esport/LouisDeLaTech/issues
Author-email: Ludovic Ortega <ludovic.ortega@lyon-esport.fr>, "Etienne 'PoPs' G." <etienne.guilluy@lyon-esport.fr>, Pierre 'DrumSlayer' Sarret <pierre.sarret@lyon-esport.fr>
License-File: LICENSE
License-File: LICENSE.fr
Keywords: discord,google
Classifier: License :: OSI Approved :: CEA CNRS Inria Logiciel Libre License, version 2.1 (CeCILL-2.1)
Classifier: Operating System :: OS Independent
Classifier: Programming Language :: Python
Classifier: Programming Language :: Python :: 3.9
Classifier: Programming Language :: Python :: 3.10
Classifier: Programming Language :: Python :: 3.11
Classifier: Programming Language :: Python :: 3.12
Classifier: Topic :: Utilities
Requires-Python: <4.0.0,>=3.9
Requires-Dist: aiosqlite~=0.21.0
Requires-Dist: cryptography~=46.0.2
Requires-Dist: discord-py~=2.6.3
Requires-Dist: google-api-python-client~=2.183.0
Requires-Dist: google-auth-httplib2~=0.2.0
Requires-Dist: httpx~=0.28.1
Requires-Dist: jinja2~=3.1.6
Requires-Dist: phonenumbers~=9.0.15
Requires-Dist: pyotp~=2.9.0
Requires-Dist: requests-oauthlib~=2.0.0
Requires-Dist: sentry-sdk~=2.39.0
Requires-Dist: tortoise-orm~=0.25.1
Requires-Dist: unidecode~=1.4.0
Provides-Extra: dev
Requires-Dist: ruff~=0.13.2; extra == 'dev'
